tabview/README.rst
tabview/__init__.py
tabview/tabview.py
tabview-1.4.3.data/data/share/doc/tabview/CHANGELOG.rst
tabview-1.4.3.data/data/share/doc/tabview/LICENSE.txt
tabview-1.4.3.data/data/share/doc/tabview/README.rst
tabview-1.4.3.data/scripts/tabview
tabview-1.4.3.dist-info/DESCRIPTION.rst
tabview-1.4.3.dist-info/METADATA
tabview-1.4.3.dist-info/RECORD
tabview-1.4.3.dist-info/WHEEL
tabview-1.4.3.dist-info/metadata.json
tabview-1.4.3.dist-info/top_level.txt
