Metadata-Version: 2.0
Name: tabview
Version: 1.4.3
Summary: A curses command-line CSV and list (tabular data) viewer
Home-page: https://github.com/firecat53/tabview
Author: Scott Hansen
Author-email: firecat4153@gmail.com
License: MIT
Download-URL: https://github.com/firecat53/tabview/tarball/1.4.3
Keywords: data spreadsheet view viewer console curses csv comma separated values
Platform: UNKNOWN
Classifier: Development Status :: 4 - Beta
Classifier: Environment :: Console
Classifier: Environment :: Console :: Curses
Classifier: Intended Audience :: Science/Research
Classifier: License :: OSI Approved :: MIT License
Classifier: Operating System :: OS Independent
Classifier: Programming Language :: Python
Classifier: Programming Language :: Python :: 2.7
Classifier: Programming Language :: Python :: 3.3
Classifier: Programming Language :: Python :: 3.4
Classifier: Programming Language :: Python :: 3.5
Classifier: Programming Language :: Python :: 3.6
Classifier: Topic :: Scientific/Engineering
Classifier: Topic :: Office/Business :: Financial :: Spreadsheet
Classifier: Topic :: Scientific/Engineering :: Visualization
Classifier: Topic :: Utilities
